{
    "caetrati": {
        "availability": "CIVIS",
        "combat": 4,
        "ranged": 5,
        "grit": 4,
        "defaultWeapon": "JAVELIN",
        "defaultShield": "SHIELD",
        "defaultBody": "NO_ARMOUR",
        "traits": [
            "SKIRMISH_SPECIALIST",
            "DETERMINED"
        ],
        "cost": 14,
        "options": [],
        "armies": [
            "celtIberian",
            "iberian",
            "lusitanian"
        ]
    },
    "tribesmenLusitanian": {
        "availability": "CIVIS",
        "combat": 4,
        "ranged": 5,
        "grit": 5,
        "defaultWeapon": "THROWING",
        "defaultShield": "SHIELD",
        "defaultBody": "NO_ARMOUR",
        "traits": [
            "WALL_OF_SPEARS"
        ],
        "cost": 12,
        "options": [],
        "armies": [
            "lusitanian"
        ]
    },
    "warriorsLusitanian": {
        "availability": "CIVIS",
        "combat": 4,
        "ranged": 5,
        "grit": 4,
        "defaultWeapon": "THROWING",
        "defaultShield": "SHIELD",
        "defaultBody": "NO_ARMOUR",
        "traits": [
            "WALL_OF_SPEARS",
            "IMPULSUM",
            "GUERRILLA",
            "DETERMINED"
        ],
        "cost": 17,
        "options": [
            "OPT_UP_PARTIAL_ARMOUR"
        ],
        "armies": [
            "lusitanian"
        ]
    },
    "scutariiCeltiberian": {
        "availability": "CIVIS",
        "combat": 4,
        "ranged": 5,
        "grit": 4,
        "defaultWeapon": "THROWING",
        "defaultShield": "HEAVY_SHIELD",
        "defaultBody": "NO_ARMOUR",
        "traits": [
            "WALL_OF_SPEARS",
            "SHIELD_OVERLAP",
            "IMPULSUM",
            "DETERMINED"
        ],
        "cost": 18,
        "options": [],
        "armies": [
            "celtIberian"
        ]
    },
    "scutariiIberianAllies": {
        "availability": "CIVIS",
        "combat": 4,
        "ranged": 5,
        "grit": 4,
        "defaultWeapon": "THROWING",
        "defaultShield": "HEAVY_SHIELD",
        "defaultBody": "NO_ARMOUR",
        "traits": [
            "WALL_OF_SPEARS",
            "GUERRILLA",
            "IMPULSUM",
            "DETERMINED",
            "ALLIES"
        ],
        "cost": 18,
        "options": [],
        "armies": [
            "celtIberian"
        ]
    },
    "scutariiIberian": {
        "availability": "CIVIS",
        "combat": 4,
        "ranged": 5,
        "grit": 4,
        "defaultWeapon": "THROWING",
        "defaultShield": "HEAVY_SHIELD",
        "defaultBody": "NO_ARMOUR",
        "traits": [
            "WALL_OF_SPEARS",
            "GUERRILLA",
            "IMPULSUM",
            "DETERMINED"
        ],
        "cost": 18,
        "options": [],
        "armies": [
            "iberian"
        ]
    },
    "scutariiCeltiberianAllies": {
        "availability": "CIVIS",
        "combat": 4,
        "ranged": 5,
        "grit": 4,
        "defaultWeapon": "THROWING",
        "defaultShield": "HEAVY_SHIELD",
        "defaultBody": "NO_ARMOUR",
        "traits": [
            "WALL_OF_SPEARS",
            "SHIELD_OVERLAP",
            "IMPULSUM",
            "DETERMINED",
            "ALLIES"
        ],
        "cost": 18,
        "options": [],
        "armies": [
            "iberian",
            "lusitanian"
        ]
    },
    "jinetes": {
        "availability": "MILITES",
        "combat": 4,
        "ranged": 5,
        "grit": 4,
        "defaultWeapon": "JAVELIN",
        "defaultShield": "SHIELD",
        "defaultBody": "NO_ARMOUR",
        "traits": [
            "MOUNTED"
        ],
        "cost": 18,
        "options": [
            "OPT_UP_PARTIAL_ARMOUR"
        ],
        "armies": [
            "celtIberian",
            "iberian",
            "lusitanian"
        ]
    },
    "veteranScutariiCeltiberan": {
        "availability": "MILITES",
        "combat": 3,
        "ranged": 5,
        "grit": 3,
        "defaultWeapon": "THROWING",
        "defaultShield": "HEAVY_SHIELD",
        "defaultBody": "PARTIAL",
        "traits": [
            "WALL_OF_SPEARS",
            "SHIELD_OVERLAP",
            "IMPULSUM",
            "DETERMINED"
        ],
        "cost": 24,
        "options": [
            "OPT_UP_FULL_ARMOUR"
        ],
        "armies": [
            "celtIberian"
        ]
    },
    "veteranScutariiIberian": {
        "availability": "MILITES",
        "combat": 3,
        "ranged": 5,
        "grit": 3,
        "defaultWeapon": "THROWING",
        "defaultShield": "HEAVY_SHIELD",
        "defaultBody": "PARTIAL",
        "traits": [
            "WALL_OF_SPEARS",
            "GUERRILLA",
            "IMPULSUM",
            "DETERMINED"
        ],
        "cost": 24,
        "options": [
            "OPT_DOWN_NO_ARMOUR"
        ],
        "armies": [
            "iberian"
        ]
    },
    "veteranLusitanian": {
        "availability": "MILITES",
        "combat": 3,
        "ranged": 5,
        "grit": 3,
        "defaultWeapon": "THROWING",
        "defaultShield": "SHIELD",
        "defaultBody": "PARTIAL",
        "traits": [
            "WALL_OF_SPEARS",
            "GUERRILLA",
            "IMPULSUM",
            "DETERMINED"
        ],
        "cost": 23,
        "options": [
            "OPT_DOWN_NO_ARMOUR"
        ],
        "armies": [
            "lusitanian"
        ]
    },
    "noblesSpanish": {
        "availability": "MILITES",
        "combat": 3,
        "ranged": 5,
        "grit": 3,
        "defaultWeapon": "CAVALRY_SPEAR",
        "defaultShield": "SHIELD",
        "defaultBody": "PARTIAL",
        "traits": [
            "MOUNTED",
            "IMPETUS",
            "EXTRA_EQUIPMENT(JAVELIN)"
        ],
        "cost": 25,
        "options": [
            "OPT_DOWN_NO_ARMOUR"
        ],
        "armies": [
            "celtIberian",
            "iberian",
            "lusitanian"
        ]
    },
    "slingersSpanish": {
        "availability": "MILITES",
        "combat": 5,
        "ranged": 5,
        "grit": 5,
        "defaultWeapon": "SLING",
        "defaultShield": "NO_ARMOUR",
        "defaultBody": "NO_ARMOUR",
        "traits": [
            "SKIRMISH_SPECIALIST"
        ],
        "cost": 8,
        "options": [
            "OPT_BUCKLER"
        ],
        "armies": [
            "celtIberian",
            "iberian",
            "lusitanian"
        ]
    }
}